{
  "currentPredictionRaw": [
    [
      0.026754897087812424,
      0.03478417173027992,
      0.0397733598947525,
      0.0382801778614521,
      0.03362566977739334,
      0.04382556304335594,
      0.03414211794734001,
      0.029484687373042107,
      0.024114396423101425,
      0.029692351818084717
    ],
    [
      0.040719833225011826,
      0.03244438022375107,
      0.04095667973160744,
      0.025652440264821053,
      0.03778943046927452,
      0.021688636392354965,
      0.022426947951316833,
      0.03310893848538399,
      0.029225923120975494,
      0.0323677696287632
    ],
    [
      0.03248920291662216,
      0.050649385899305344,
      0.038516126573085785,
      0.04612923413515091,
      0.03270754590630531,
      0.03280729800462723,
      0.027215542271733284,
      0.02365724928677082,
      0.034682050347328186,
      0.03028806671500206
    ]
  ],
  "currentPrediction": [
    {
      "name": "Markov Model",
      "predictions": [
        [
          1,
          3,
          8
        ]
      ]
    },
    {
      "name": "MarkovBayesian Model",
      "predictions": [
        [
          0,
          4,
          5
        ]
      ]
    },
    {
      "name": "PoissonMonteCarlo Model",
      "predictions": [
        [
          3,
          4,
          5
        ]
      ]
    },
    {
      "name": "PoissonMarkov Model",
      "predictions": [
        [
          3,
          4,
          2
        ]
      ]
    },
    {
      "name": "LaplaceMonteCarlo Model",
      "predictions": [
        [
          5,
          4,
          5
        ]
      ]
    },
    {
      "name": "HybridStatisticalModel",
      "predictions": [
        [
          4,
          6,
          8
        ]
      ]
    },
    {
      "name": "LSTM Base Model",
      "predictions": [
        [
          5,
          2,
          1
        ]
      ]
    }
  ],
  "realResult": [
    4,
    4,
    9
  ],
  "newPrediction": [
    {
      "name": "Markov Model",
      "predictions": [
        [
          7,
          8,
          9
        ]
      ]
    },
    {
      "name": "MarkovBayesian Model",
      "predictions": [
        [
          4,
          6,
          7
        ]
      ]
    },
    {
      "name": "PoissonMonteCarlo Model",
      "predictions": [
        [
          2,
          3,
          4
        ]
      ]
    },
    {
      "name": "PoissonMarkov Model",
      "predictions": [
        [
          6,
          2,
          4
        ]
      ]
    },
    {
      "name": "LaplaceMonteCarlo Model",
      "predictions": [
        [
          3,
          4,
          4
        ]
      ]
    },
    {
      "name": "HybridStatisticalModel",
      "predictions": [
        [
          8,
          7,
          9
        ]
      ]
    },
    {
      "name": "LSTM Base Model",
      "predictions": [
        [
          1,
          0,
          1
        ]
      ]
    }
  ],
  "newPredictionRaw": [
    [
      0.029029574245214462,
      0.06454429030418396,
      0.042219240218400955,
      0.03415882587432861,
      0.02791752852499485,
      0.032424528151750565,
      0.03163385018706322,
      0.03955704718828201,
      0.01837390661239624,
      0.03480002284049988
    ],
    [
      0.06345697492361069,
      0.0277900118380785,
      0.019287191331386566,
      0.022755451500415802,
      0.03994710370898247,
      0.012546909973025322,
      0.010491435416042805,
      0.026058662682771683,
      0.03753531351685524,
      0.03264516219496727
    ],
    [
      0.012842884287238121,
      0.07137954235076904,
      0.03346281871199608,
      0.06680258363485336,
      0.021612707525491714,
      0.033707115799188614,
      0.026235701516270638,
      0.0213671512901783,
      0.03176240995526314,
      0.03365403413772583
    ]
  ],
  "matchingNumbers": {
    "model": "MarkovBayesian Model",
    "prediction": [
      0,
      4,
      5
    ],
    "matching_numbers": [
      4
    ],
    "match_count": 1
  },
  "labels": [
    0,
    1,
    2,
    3,
    4,
    5,
    6,
    7,
    8,
    9
  ],
  "numberFrequency": {
    "7": 0.14285714285714285,
    "8": 0.09523809523809523,
    "9": 0.09523809523809523,
    "4": 0.23809523809523808,
    "6": 0.09523809523809523,
    "2": 0.09523809523809523,
    "3": 0.09523809523809523,
    "1": 0.09523809523809523,
    "0": 0.047619047619047616
  }
}