{
  "currentPredictionRaw": [
    [
      0.155677929520607,
      0.09303738921880722,
      0.07151401787996292,
      0.12070222198963165,
      0.0898255780339241,
      0.10010275989770889,
      0.047854892909526825,
      0.04472225159406662,
      0.16851364076137543,
      0.10804931074380875
    ],
    [
      0.13006393611431122,
      0.07169073075056076,
      0.027618078514933586,
      0.05671349912881851,
      0.051197271794080734,
      0.05406532436609268,
      0.18007098138332367,
      0.0425478033721447,
      0.25553110241889954,
      0.13050127029418945
    ],
    [
      0.05473697558045387,
      0.10708782821893692,
      0.08316034823656082,
      0.08974124491214752,
      0.24183352291584015,
      0.08321566134691238,
      0.16569863259792328,
      0.062183625996112823,
      0.06359784305095673,
      0.04874427989125252
    ]
  ],
  "currentPrediction": [
    {
      "name": "LSTM Base Model",
      "predictions": [
        [
          8,
          8,
          4
        ]
      ]
    },
    {
      "name": "Markov Model",
      "predictions": [
        [
          4,
          7,
          4
        ]
      ]
    },
    {
      "name": "MarkovBayesian Model",
      "predictions": [
        [
          2,
          3,
          4
        ]
      ]
    },
    {
      "name": "PoissonMonteCarlo Model",
      "predictions": [
        [
          0,
          5,
          7
        ]
      ]
    },
    {
      "name": "PoissonMarkov Model",
      "predictions": [
        [
          9,
          4,
          2
        ]
      ]
    },
    {
      "name": "LaplaceMonteCarlo Model",
      "predictions": [
        [
          3,
          3,
          4
        ]
      ]
    },
    {
      "name": "HybridStatisticalModel",
      "predictions": [
        [
          1,
          4,
          5
        ]
      ]
    }
  ],
  "realResult": [
    3,
    6,
    1
  ],
  "newPrediction": [
    {
      "name": "LSTM Base Model",
      "predictions": [
        [
          5,
          6,
          3
        ]
      ]
    },
    {
      "name": "Markov Model",
      "predictions": [
        [
          6,
          2,
          5
        ]
      ]
    },
    {
      "name": "MarkovBayesian Model",
      "predictions": [
        [
          1,
          2,
          3
        ]
      ]
    },
    {
      "name": "PoissonMonteCarlo Model",
      "predictions": [
        [
          0,
          3,
          7
        ]
      ]
    },
    {
      "name": "PoissonMarkov Model",
      "predictions": [
        [
          9,
          1,
          6
        ]
      ]
    },
    {
      "name": "LaplaceMonteCarlo Model",
      "predictions": [
        [
          3,
          5,
          3
        ]
      ]
    },
    {
      "name": "HybridStatisticalModel",
      "predictions": [
        [
          3,
          1,
          2
        ]
      ]
    }
  ],
  "newPredictionRaw": [
    [
      0.12143981456756592,
      0.07975471764802933,
      0.04336594045162201,
      0.0490490086376667,
      0.08618747442960739,
      0.2035883367061615,
      0.09015607833862305,
      0.12197289615869522,
      0.11585650593042374,
      0.08862921595573425
    ],
    [
      0.07581440359354019,
      0.09398650377988815,
      0.02805665135383606,
      0.06900177896022797,
      0.07529941946268082,
      0.14076580107212067,
      0.19310612976551056,
      0.06669428944587708,
      0.1433723270893097,
      0.11390267312526703
    ],
    [
      0.06337077170610428,
      0.058955926448106766,
      0.08911111205816269,
      0.23235097527503967,
      0.0797368586063385,
      0.09229641407728195,
      0.20144064724445343,
      0.04794978350400925,
      0.0819699838757515,
      0.05281756445765495
    ]
  ],
  "matchingNumbers": {
    "model": "MarkovBayesian Model",
    "prediction": [
      2,
      3,
      4
    ],
    "matching_numbers": [
      3
    ],
    "match_count": 1
  },
  "labels": [
    0,
    1,
    2,
    3,
    4,
    5,
    6,
    7,
    8,
    9
  ],
  "numberFrequency": {
    "5": 0.14285714285714285,
    "6": 0.14285714285714285,
    "3": 0.2857142857142857,
    "2": 0.14285714285714285,
    "1": 0.14285714285714285,
    "0": 0.047619047619047616,
    "7": 0.047619047619047616,
    "9": 0.047619047619047616
  }
}