{
  "currentPredictionRaw": [],
  "currentPrediction": [
    {
      "name": "HybridStatisticalModel",
      "predictions": [
        [
          1,
          15,
          3,
          5,
          16,
          18,
          21
        ]
      ]
    }
  ],
  "realResult": [
    11,
    15,
    24,
    26,
    32,
    37,
    2
  ],
  "newPrediction": [
    {
      "name": "HybridStatisticalModel",
      "predictions": [
        [
          2,
          4,
          3,
          15,
          19,
          21,
          1
        ]
      ]
    }
  ],
  "newPredictionRaw": [],
  "matchingNumbers": {
    "model": "HybridStatisticalModel",
    "prediction": [
      1,
      15,
      3,
      5,
      16,
      18,
      21
    ],
    "matching_numbers": [
      15
    ],
    "match_count": 1
  },
  "labels": [],
  "numberFrequency": []
}