{
  "currentPredictionRaw": [],
  "currentPrediction": [
    {
      "name": "HybridStatisticalModel",
      "predictions": [
        [
          4,
          5,
          1,
          2,
          24,
          32,
          39
        ]
      ]
    }
  ],
  "realResult": [
    26,
    31,
    33,
    34,
    37,
    44,
    2
  ],
  "newPrediction": [
    {
      "name": "HybridStatisticalModel",
      "predictions": [
        [
          1,
          39,
          3,
          4,
          5,
          11,
          20
        ]
      ]
    }
  ],
  "newPredictionRaw": [],
  "matchingNumbers": {
    "model": "HybridStatisticalModel",
    "prediction": [
      4,
      5,
      1,
      2,
      24,
      32,
      39
    ],
    "matching_numbers": [
      2
    ],
    "match_count": 1
  },
  "labels": [],
  "numberFrequency": []
}