{
  "currentPredictionRaw": [],
  "currentPrediction": [
    {
      "name": "HybridStatisticalModel",
      "predictions": [
        [
          3,
          2,
          5,
          6,
          15,
          44,
          1
        ]
      ]
    }
  ],
  "realResult": [
    19,
    29,
    42,
    45,
    48,
    5,
    7
  ],
  "newPrediction": [
    {
      "name": "HybridStatisticalModel",
      "predictions": [
        [
          8,
          7,
          1,
          2,
          3,
          6,
          4
        ]
      ]
    }
  ],
  "newPredictionRaw": [],
  "matchingNumbers": {
    "model": "HybridStatisticalModel",
    "prediction": [
      3,
      2,
      5,
      6,
      15,
      44,
      1
    ],
    "matching_numbers": [
      5
    ],
    "match_count": 1
  },
  "labels": [],
  "numberFrequency": []
}