{
  "currentPredictionRaw": [],
  "currentPrediction": [
    {
      "name": "HybridStatisticalModel",
      "predictions": [
        [
          7,
          3,
          6,
          9,
          2,
          5,
          8
        ]
      ]
    }
  ],
  "realResult": [
    4,
    9,
    35,
    46,
    50,
    8,
    11
  ],
  "newPrediction": [
    {
      "name": "HybridStatisticalModel",
      "predictions": [
        [
          9,
          2,
          3,
          6,
          7,
          8,
          10
        ]
      ]
    }
  ],
  "newPredictionRaw": [],
  "matchingNumbers": {
    "model": "HybridStatisticalModel",
    "prediction": [
      7,
      3,
      6,
      9,
      2,
      5,
      8
    ],
    "matching_numbers": [
      8,
      9
    ],
    "match_count": 2
  },
  "labels": [],
  "numberFrequency": []
}