{
  "currentPredictionRaw": [],
  "currentPrediction": [
    {
      "name": "HybridStatisticalModel",
      "predictions": [
        [
          6,
          3,
          5,
          7,
          9,
          2,
          8
        ]
      ]
    }
  ],
  "realResult": [
    13,
    22,
    23,
    44,
    49,
    3,
    5
  ],
  "newPrediction": [
    {
      "name": "HybridStatisticalModel",
      "predictions": [
        [
          3,
          7,
          2,
          6,
          9,
          43,
          5
        ]
      ]
    }
  ],
  "newPredictionRaw": [],
  "matchingNumbers": {
    "model": "HybridStatisticalModel",
    "prediction": [
      6,
      3,
      5,
      7,
      9,
      2,
      8
    ],
    "matching_numbers": [
      3,
      5
    ],
    "match_count": 2
  },
  "labels": [],
  "numberFrequency": []
}