{
  "currentPredictionRaw": [
    [
      0.00040551903657615185,
      1.6059509584172885e-38,
      1.253451370475389e-10,
      1.238633444700099e-06,
      9.323806807515211e-06,
      9.225430393698773e-18,
      0.999583899974823,
      3.229056176254746e-25,
      2.852581780194122e-31,
      4.5099093405464655e-33
    ],
    [
      1.418720404610816e-28,
      0.0,
      6.086489090506575e-09,
      0.0,
      4.571094781474686e-37,
      0.0,
      5.315501183691856e-38,
      1.0,
      2.4815118848664497e-09,
      1.7231892404789755e-25
    ],
    [
      4.949135755829297e-17,
      0.0,
      0.9999822378158569,
      0.0,
      1.725501351756975e-05,
      0.0,
      0.0,
      4.4764803419639065e-07,
      0.0,
      0.0
    ]
  ],
  "currentPrediction": [
    {
      "name": "LSTM Base Model",
      "predictions": [
        [
          6,
          7,
          2
        ],
        [
          0,
          2,
          7
        ]
      ]
    },
    {
      "name": "LSTM Refined Model",
      "predictions": [
        [
          7,
          0,
          6
        ],
        [
          1,
          6,
          2
        ]
      ]
    },
    {
      "name": "ARIMA Model",
      "predictions": [
        [
          4,
          5,
          6
        ]
      ]
    },
    {
      "name": "Markov Model",
      "predictions": [
        [
          8,
          2,
          7
        ]
      ]
    },
    {
      "name": "MarkovBayesian Model",
      "predictions": [
        [
          2,
          3,
          4
        ]
      ]
    },
    {
      "name": "PoissonMonteCarlo Model",
      "predictions": [
        [
          2,
          3,
          5
        ]
      ]
    },
    {
      "name": "LaplaceMonteCarlo Model",
      "predictions": [
        [
          4,
          5,
          4
        ]
      ]
    },
    {
      "name": "HybridStatisticalModel",
      "predictions": [
        [
          4,
          6,
          0
        ]
      ]
    }
  ],
  "realResult": [
    8,
    7,
    9
  ],
  "newPrediction": [
    {
      "name": "LSTM Base Model",
      "predictions": [
        [
          8,
          1,
          7
        ],
        [
          7,
          5,
          8
        ]
      ]
    },
    {
      "name": "LSTM Refined Model",
      "predictions": [
        [
          7,
          6,
          8
        ],
        [
          5,
          1,
          2
        ]
      ]
    },
    {
      "name": "ARIMA Model",
      "predictions": [
        [
          4,
          5,
          6
        ]
      ]
    },
    {
      "name": "Markov Model",
      "predictions": [
        [
          1,
          2,
          3
        ]
      ]
    },
    {
      "name": "MarkovBayesian Model",
      "predictions": [
        [
          1,
          3,
          5
        ]
      ]
    },
    {
      "name": "PoissonMonteCarlo Model",
      "predictions": [
        [
          2,
          7,
          9
        ]
      ]
    },
    {
      "name": "LaplaceMonteCarlo Model",
      "predictions": [
        [
          3,
          3,
          5
        ]
      ]
    },
    {
      "name": "HybridStatisticalModel",
      "predictions": [
        [
          6,
          5,
          8
        ]
      ]
    }
  ],
  "newPredictionRaw": [
    [
      0.0,
      1.812138517724812e-30,
      2.797215234550053e-29,
      1.074968113692431e-37,
      0.0,
      0.0,
      0.0,
      2.8306167223490775e-05,
      0.9999717473983765,
      3.0453233268445956e-09
    ],
    [
      0.0,
      0.9999967813491821,
      0.0,
      1.8682621851743134e-29,
      0.0,
      3.1720690003567142e-06,
      0.0,
      0.0,
      0.0,
      9.625923322320595e-12
    ],
    [
      2.6986448159194773e-27,
      0.0,
      4.668135744623214e-08,
      0.0,
      6.927499990905197e-34,
      0.0,
      1.1458637714798744e-36,
      1.0,
      1.2448746200544036e-10,
      9.21347382543519e-26
    ]
  ],
  "matchingNumbers": {
    "model": "Markov Model",
    "prediction": [
      8,
      2,
      7
    ],
    "matching_numbers": [
      8,
      7
    ],
    "match_count": 2
  },
  "labels": [
    0,
    1,
    2,
    3,
    4,
    5,
    6,
    7,
    8,
    9
  ],
  "numberFrequency": {
    "3": 0.09782707933899389,
    "2": 0.10097690130557838,
    "6": 0.10006390943120606,
    "8": 0.1007486533369853,
    "9": 0.10001825983748745,
    "0": 0.10211814114854378,
    "5": 0.09887701999452204,
    "4": 0.10143339724276454,
    "1": 0.09997261024376883,
    "7": 0.09796402812014973
  }
}